{
    "题型分类": [
      {
        "题型": "细节题",
        "题型特征": "针对6w1h提问，细节题问题一般不掺杂主观内容，而是针对文章的某个具体细节，如时间、地点、人物、原因、结果、条件、现象等进行提问，所给选项有三个为干扰项，这些干扰项有的是片面性的，有的是部分正确的，还有的属于文中并未涉及的。",
        "做题方法": [
          "1. 应仔细阅读题目，弄清楚题目的具体要求，读懂选项内容，找出题目或选项中的关键词。",
          "2. 利用关键词返回到原文中，找出与原文相对应的句子。关键词的确定是解题的重点。",
          "3. 将确定的句子与四个选项进行对照，通常选项的表述与原文句子有所差别，尽管不是文章原句，却是对其进行的同义转述，一定要根据原文句子进行匹配。"
        ]
        
      },
      {
        "题型": "猜词题",
        "形式": [
          {
            "类型": "词汇题",
            "题型特征": "在题干中明确指出原文的单词或词组，要求辨其意。",
            "做题方法": [
                "寻找同义词词组;代入替换法", "该单词的上下文"
            ]
          },
          {
            "类型": "指代题",
            "题型特征": "在题干中明确指出原文中某个代词，要求辨别其指代关系，即 it, that, one",
            "做题方法": "返回原文定位此指代词，搜索其指代的词、词组或句子"
          },
          {
            "类型": "句子理解题",
            "题型特征": "在题干中明确指出原文中的某句话，要求理解其意思。",
            "做题方法": ["返回原文，对出题句进行语法、句法、词法的分析，精确了解其含义。",
            "重要的不是上下文，而是该句本身。正确答案与原文是同义关系，与原文其他无关联，选项一般无绝对 的判断，有绝对判断的则必错。"
          ]
          }
        ]
      },
      {
        "题型": "推论题",
        "题型特征": "infer imply",
        "做题方法": ["每个选项都列举了文章的一个事实(或错误事实)，我们要找的是哪一个符合原文。",
        "如果四个选项之中都没明确提到，那么与原文意思最接近，所用推理步骤最少的就是正确答案。",
        "尤其要重视话中有话的陈述句或比喻句或反语或长难句，这些地方一般是分散列举题出题所在。"
      ]
      },
      {
        "题型": "态度题",
        "题型特征": [
            "attitude",
            "依据中心句推论"
        ],
        "做题方法": ["识别作者态度有以下方法;(1)依据中心句推论(2)当作者态度未明确提出时，要找文章中带有褒贬意义的词(3)根 据所举例子的正负来判断，只提一方，则不中立;两方均提，不管例子有多少，是否平衡，都中立。",
        "作者态度只分三类(1)支持，赞同，乐观(2)客观，中立(3)反对，批评，怀疑，悲观。除此之外没有其他作者态 度。有些选项一定不是答案 indifferent, subjective(主观), biased, puzzling 等"
      ]
      },
      {
        "题型": "主旨题",
        "题型特征": [
            "best title, main idea, main problem,conclusion, best title, the writing purpose。",
            "(1)正确选项一般不含细节信息，并不含过分肯定或绝对意义的词 (2)错误选项的特点是就事论事，或细节信息鲜明，或过于笼统。"
        ],
        "做题方法": [
          "理解首末段，首末句",
          "警惕文章中间或前后段意转折",
          "转折句可能是主题句",
          "作者有意识重复的观点是主旨",
          "疑问句的解答是主旨"
        ]
      }
    ]
  }
  